[
  {
    "grade": 5,
    "subject": "Sosyal Bilgiler",
    "unit": "1. Ünite: Birey ve Toplum",
    "question": "Toplumda farklı gruplar içinde bulunduğumuzda üzerimize düşen görevlere ne denir?",
    "option1": "Rol",
    "option2": "Hak",
    "option3": "Sorumluluk",
    "option4": "Olay",
    "correctAnswer": 2,
    "difficulty": "easy",
    "explanation": "Rollerin gerektirdiği davranışları yerine getirmeye sorumluluk denir.",
    "theme": "1. Ünite: Birey ve Toplum"
  },
  {
    "grade": 5,
    "subject": "Sosyal Bilgiler",
    "unit": "1. Ünite: Birey ve Toplum",
    "question": "Okulda öğrenci, evde evlat olan birinin farklı gruplarda farklı konumlarda olması neyi ifade eder?",
    "option1": "Bireyin aynı anda birden fazla 'Rol'ü olabileceğini",
    "option2": "Sadece bir hakkı olduğunu",
    "option3": "Sorun yaşadığını",
    "option4": "Grup kurallarına uymadığını",
    "correctAnswer": 0,
    "difficulty": "easy",
    "explanation": "İnsanlar yer aldıkları gruplara göre takım kaptanı, öğrenci, evlat gibi roller alırlar.",
    "theme": "1. Ünite: Birey ve Toplum"
  },
  {
    "grade": 5,
    "subject": "Sosyal Bilgiler",
    "unit": "1. Ünite: Birey ve Toplum",
    "question": "Bir olayın birden çok nedeni ve birden çok sonucu olmasına ne ad verilir?",
    "option1": "Empati",
    "option2": "Olayların çok boyutluluğu",
    "option3": "Sorumluluk",
    "option4": "Kronoloji",
    "correctAnswer": 1,
    "difficulty": "medium",
    "explanation": "Trafik kazası, göç gibi olaylar herkesi farklı etkiler ve çok boyutludur.",
    "theme": "1. Ünite: Birey ve Toplum"
  },
  {
    "grade": 5,
    "subject": "Sosyal Bilgiler",
    "unit": "1. Ünite: Birey ve Toplum",
    "question": "Aşağıdakilerden hangisi bir öğrencinin sahip olduğu temel haklardan biridir?",
    "option1": "Odayı toplamak",
    "option2": "Vergi vermek",
    "option3": "Eğitim (Öğrenim) görmek",
    "option4": "Askere gitmek",
    "correctAnswer": 2,
    "difficulty": "easy",
    "explanation": "Eğitim ve sağlık devletin çocuklara sağladığı devredilemez haklardandır.",
    "theme": "1. Ünite: Birey ve Toplum"
  },
  {
    "grade": 5,
    "subject": "Sosyal Bilgiler",
    "unit": "1. Ünite: Birey ve Toplum",
    "question": "Tüm dünyada çocuk haklarını korumak amacıyla kurulan Birleşmiş Milletler yardım fonu hangisidir?",
    "option1": "TEMA",
    "option2": "KIZILAY",
    "option3": "UNICEF",
    "option4": "LÖSEV",
    "correctAnswer": 2,
    "difficulty": "medium",
    "explanation": "BM Çocuklara Yardım Fonu olan UNICEF çocuk hakları için çalışır.",
    "theme": "1. Ünite: Birey ve Toplum"
  },
  {
    "grade": 5,
    "subject": "Sosyal Bilgiler",
    "unit": "1. Ünite: Birey ve Toplum",
    "question": "Haklarımız ihlal edildiğinde aşağıdakilerden hangisini yapmalıyız?",
    "option1": "Sessiz kalıp kabullenmeliyiz",
    "option2": "Dilekçe hakkımızı kullanarak yasal yollara başvurmalıyız",
    "option3": "Kavga etmeliyiz",
    "option4": "Şiddet uygulamalıyız",
    "correctAnswer": 1,
    "difficulty": "medium",
    "explanation": "Medeni insanlar haklarını yasal ve resmi merciler (dilekçe, hakem heyeti) üzerinden arar.",
    "theme": "1. Ünite: Birey ve Toplum"
  },
  {
    "grade": 5,
    "subject": "Sosyal Bilgiler",
    "unit": "1. Ünite: Birey ve Toplum",
    "question": "Kaç yaşına kadar her birey yasal olarak 'Çocuk' kabul edilir?",
    "option1": "12",
    "option2": "15",
    "option3": "18",
    "option4": "21",
    "correctAnswer": 2,
    "difficulty": "easy",
    "explanation": "Çocuk Hakları Sözleşmesi'ne göre 18 yaşını doldurmamış herkes çocuktur.",
    "theme": "1. Ünite: Birey ve Toplum"
  },
  {
    "grade": 5,
    "subject": "Sosyal Bilgiler",
    "unit": "1. Ünite: Birey ve Toplum",
    "question": "Bireyin içinde bulunduğu grup veya kuruma göre kazandığı duruma ne denir?",
    "option1": "Hak",
    "option2": "Rol",
    "option3": "Kural",
    "option4": "Yetenek",
    "correctAnswer": 1,
    "difficulty": "hard",
    "explanation": "Ailede evlat, okulda öğrenci gibi konumlarımız birer roldür.",
    "theme": "1. Ünite: Birey ve Toplum"
  },
  {
    "grade": 5,
    "subject": "Sosyal Bilgiler",
    "unit": "1. Ünite: Birey ve Toplum",
    "question": "Aşağıdaki rollerden hangisi doğuştan sahip olduğumuz biyolojik rollerden biridir?",
    "option1": "Sınıf başkanı olmak",
    "option2": "Doktor olmak",
    "option3": "Evlat / Kardeş olmak",
    "option4": "Kaleci olmak",
    "correctAnswer": 2,
    "difficulty": "hard",
    "explanation": "Evlat olmak doğuştan gelir, doktorluk veya başkanlık sonradan çabayla kazanılır.",
    "theme": "1. Ünite: Birey ve Toplum"
  },
  {
    "grade": 5,
    "subject": "Sosyal Bilgiler",
    "unit": "1. Ünite: Birey ve Toplum",
    "question": "Sosyal Bilgiler dersinin bize kazandırdığı en önemli özellik nedir?",
    "option1": "Sadece iyi matematik bilmek",
    "option2": "Hak ve sorumluluklarını bilen etkin (iyi) vatandaş olmak",
    "option3": "Uzayı keşfetmek",
    "option4": "Doktor olmak",
    "correctAnswer": 1,
    "difficulty": "medium",
    "explanation": "Sosyal bilgiler bizi topluma duyarlı, hakkını bilen vatandaşlar olarak yetiştirir.",
    "theme": "1. Ünite: Birey ve Toplum"
  },
  {
    "grade": 5,
    "subject": "Sosyal Bilgiler",
    "unit": "2. Ünite: Kültür ve Miras",
    "question": "Tarihte yazıyı icat ederek İlk Çağ'ı (tarihi devirleri) başlatan Mezopotamya uygarlığı hangisidir?",
    "option1": "Sümerler",
    "option2": "Hititler",
    "option3": "Lidyalılar",
    "option4": "Frigler",
    "correctAnswer": 0,
    "difficulty": "easy",
    "explanation": "Çivi yazısını bularak tarihi başlatan uygarlık Sümerler'dir.",
    "theme": "2. Ünite: Kültür ve Miras"
  },
  {
    "grade": 5,
    "subject": "Sosyal Bilgiler",
    "unit": "2. Ünite: Kültür ve Miras",
    "question": "Parayı icat edip takas usulüne son veren, Kral Yolu'nu yapan Anadolu uygarlığı kimdir?",
    "option1": "İyonlar",
    "option2": "Lidyalılar",
    "option3": "Urartular",
    "option4": "Sümerler",
    "correctAnswer": 1,
    "difficulty": "easy",
    "explanation": "Lidyalılar madeni parayı bularak ticarette devrim yapmıştır.",
    "theme": "2. Ünite: Kültür ve Miras"
  },
  {
    "grade": 5,
    "subject": "Sosyal Bilgiler",
    "unit": "2. Ünite: Kültür ve Miras",
    "question": "Doğada insan eli değmeden, kendiliğinden rüzgar ve sularla oluşmuş güzelliklere ne ad verilir?",
    "option1": "Tarihi eser",
    "option2": "Beşeri unsur",
    "option3": "Doğal varlık",
    "option4": "Müze",
    "correctAnswer": 2,
    "difficulty": "medium",
    "explanation": "Pamukkale Travertenleri, Peri Bacaları gibi yapılar doğal varlıklardır.",
    "theme": "2. Ünite: Kültür ve Miras"
  },
  {
    "grade": 5,
    "subject": "Sosyal Bilgiler",
    "unit": "2. Ünite: Kültür ve Miras",
    "question": "Geçmişte yaşayan insanların kendi elleriyle inşa ettikleri ve günümüze ulaşan (Efes Antik Kenti gibi) yapılara ne denir?",
    "option1": "Doğal varlık",
    "option2": "Tarihi eser",
    "option3": "Bitki örtüsü",
    "option4": "Gelenek",
    "correctAnswer": 1,
    "difficulty": "easy",
    "explanation": "İnsan emeğiyle yapılan tarihi binalar tarihi eser statüsündedir.",
    "theme": "2. Ünite: Kültür ve Miras"
  },
  {
    "grade": 5,
    "subject": "Sosyal Bilgiler",
    "unit": "2. Ünite: Kültür ve Miras",
    "question": "Tarihte bilinen ilk yazılı antlaşma olan Kadeş Antlaşması hangi iki devlet arasında yapılmıştır?",
    "option1": "Lidyalılar - Frigler",
    "option2": "Hititler - Mısırlılar",
    "option3": "İyonlar - Urartular",
    "option4": "Sümerler - Asurlar",
    "correctAnswer": 1,
    "difficulty": "hard",
    "explanation": "Hititler ve Mısırlılar tarihteki ilk barış antlaşmasını imzalamıştır.",
    "theme": "2. Ünite: Kültür ve Miras"
  },
  {
    "grade": 5,
    "subject": "Sosyal Bilgiler",
    "unit": "2. Ünite: Kültür ve Miras",
    "question": "Öküz kesmenin ve saban (tarım aleti) kırmanın cezasının ölüm olduğu, tarıma en çok önem veren Anadolu uygarlığı kimdir?",
    "option1": "Frigler",
    "option2": "Lidyalılar",
    "option3": "Urartular",
    "option4": "Asurlar",
    "correctAnswer": 0,
    "difficulty": "medium",
    "explanation": "Frigler geçimini tarımdan sağladığı için sert tarım kanunları koymuştur.",
    "theme": "2. Ünite: Kültür ve Miras"
  },
  {
    "grade": 5,
    "subject": "Sosyal Bilgiler",
    "unit": "2. Ünite: Kültür ve Miras",
    "question": "Hangisi yöreden yöreye değişen kültürel özelliklerimizdendir?",
    "option1": "Halk oyunları ve yemekler",
    "option2": "Para birimimiz",
    "option3": "Trafik kuralları",
    "option4": "Okul saatleri",
    "correctAnswer": 0,
    "difficulty": "easy",
    "explanation": "Horon, Zeybek, mantı, kebap gibi ögeler kültürel farklılıklarımızdır.",
    "theme": "2. Ünite: Kültür ve Miras"
  },
  {
    "grade": 5,
    "subject": "Sosyal Bilgiler",
    "unit": "2. Ünite: Kültür ve Miras",
    "question": "Aşağıdakilerden hangisi milli bayramlarımızdan biri DEĞİLDİR?",
    "option1": "23 Nisan",
    "option2": "29 Ekim",
    "option3": "Ramazan Bayramı",
    "option4": "30 Ağustos",
    "correctAnswer": 2,
    "difficulty": "medium",
    "explanation": "Ramazan Bayramı dini bayramdır, milli bayramlar devleti ve zaferleri kutlar.",
    "theme": "2. Ünite: Kültür ve Miras"
  },
  {
    "grade": 5,
    "subject": "Sosyal Bilgiler",
    "unit": "2. Ünite: Kültür ve Miras",
    "question": "Hititlerin tanrılara hesap vermek için yazdıkları 'Anal' adı verilen yıllıkların önemi nedir?",
    "option1": "İlk ticaret anlaşmasıdır.",
    "option2": "Doğruları ve hataları yazdıkları için objektif (tarafsız) tarihçiliği başlatmıştır.",
    "option3": "Şiir kitabıdır.",
    "option4": "İlk para örneğidir.",
    "correctAnswer": 1,
    "difficulty": "hard",
    "explanation": "Korkmadan yenilgilerini bile tanrıya yazarak anlattıkları için tarafsız tarihçiliktir.",
    "theme": "2. Ünite: Kültür ve Miras"
  },
  {
    "grade": 5,
    "subject": "Sosyal Bilgiler",
    "unit": "2. Ünite: Kültür ve Miras",
    "question": "Dicle ve Fırat nehirleri arasında kalan verimli topraklara (Sümer ve Asurların kurulduğu bölgeye) eski çağlarda ne ad verilirdi?",
    "option1": "Anadolu",
    "option2": "Mısır",
    "option3": "Mezopotamya",
    "option4": "Balkanlar",
    "correctAnswer": 2,
    "difficulty": "medium",
    "explanation": "İki nehir arasındaki bereketli bölge Mezopotamya (Irak ve Suriye civarı) olarak bilinir.",
    "theme": "2. Ünite: Kültür ve Miras"
  },
  {
    "grade": 5,
    "subject": "Sosyal Bilgiler",
    "unit": "3. Ünite: İnsanlar, Yerler ve Çevreler",
    "question": "Dünya'nın ve ülkemizin yüzey şekillerini (dağ, ova, göl) gösteren haritalara ne ad verilir?",
    "option1": "Siyasi Harita",
    "option2": "Fiziki Harita",
    "option3": "Kroki",
    "option4": "İklim Haritası",
    "correctAnswer": 1,
    "difficulty": "easy",
    "explanation": "Yer şekillerini ve yükseltileri renklerle gösteren harita fiziki haritadır.",
    "theme": "3. Ünite: İnsanlar, Yerler ve Çevreler"
  },
  {
    "grade": 5,
    "subject": "Sosyal Bilgiler",
    "unit": "3. Ünite: İnsanlar, Yerler ve Çevreler",
    "question": "Fiziki haritalarda ovalar ve deniz seviyesindeki alçak yerler hangi renkle gösterilir?",
    "option1": "Kahverengi",
    "option2": "Sarı",
    "option3": "Yeşil",
    "option4": "Mavi",
    "correctAnswer": 2,
    "difficulty": "medium",
    "explanation": "Yeşil renk ormanı değil, deniz seviyesine yakın alçak yerleri (ovaları) temsil eder.",
    "theme": "3. Ünite: İnsanlar, Yerler ve Çevreler"
  },
  {
    "grade": 5,
    "subject": "Sosyal Bilgiler",
    "unit": "3. Ünite: İnsanlar, Yerler ve Çevreler",
    "question": "Yüksek dağlık bölgeler fiziki haritada hangi renkle çizilir?",
    "option1": "Kahverengi",
    "option2": "Yeşil",
    "option3": "Mavi",
    "option4": "Sarı",
    "correctAnswer": 0,
    "difficulty": "easy",
    "explanation": "Yükselti arttıkça haritada renk sarıdan kahverengiye döner.",
    "theme": "3. Ünite: İnsanlar, Yerler ve Çevreler"
  },
  {
    "grade": 5,
    "subject": "Sosyal Bilgiler",
    "unit": "3. Ünite: İnsanlar, Yerler ve Çevreler",
    "question": "Yazları sıcak ve kurak, kışları ılık ve yağışlı geçen; bitki örtüsü maki olan iklim tipi hangisidir?",
    "option1": "Karasal iklim",
    "option2": "Akdeniz iklimi",
    "option3": "Karadeniz iklimi",
    "option4": "Muson iklimi",
    "correctAnswer": 1,
    "difficulty": "medium",
    "explanation": "Ege ve Akdeniz kıyılarında görülen, kar yağışının nadir olduğu iklimdir.",
    "theme": "3. Ünite: İnsanlar, Yerler ve Çevreler"
  },
  {
    "grade": 5,
    "subject": "Sosyal Bilgiler",
    "unit": "3. Ünite: İnsanlar, Yerler ve Çevreler",
    "question": "Ülkemizde iç kesimlerde (İç Anadolu, Doğu Anadolu) görülen, yazları sıcak, kışları çok soğuk ve kar yağışlı (bozkır) iklimi hangisidir?",
    "option1": "Akdeniz",
    "option2": "Karadeniz",
    "option3": "Karasal iklim",
    "option4": "Okyanusal iklim",
    "correctAnswer": 2,
    "difficulty": "medium",
    "explanation": "Karasal iklimde deniz etkisi olmadığı için hava çok soğur ve bozkırlar oluşur.",
    "theme": "3. Ünite: İnsanlar, Yerler ve Çevreler"
  },
  {
    "grade": 5,
    "subject": "Sosyal Bilgiler",
    "unit": "3. Ünite: İnsanlar, Yerler ve Çevreler",
    "question": "Aşırı yağışların ve eriyen karların aniden taşkınlara yol açmasına ne denir?",
    "option1": "Deprem",
    "option2": "Sel",
    "option3": "Çığ",
    "option4": "Kuraklık",
    "correctAnswer": 1,
    "difficulty": "easy",
    "explanation": "Su taşkınları can ve mal kaybına neden olan sel afetidir.",
    "theme": "3. Ünite: İnsanlar, Yerler ve Çevreler"
  },
  {
    "grade": 5,
    "subject": "Sosyal Bilgiler",
    "unit": "3. Ünite: İnsanlar, Yerler ve Çevreler",
    "question": "Eğimli yamaçlarda, ormansız yerlerde karların büyük kütleler halinde kopup kaymasına ne ad verilir?",
    "option1": "Erozyon",
    "option2": "Heyelan",
    "option3": "Çığ",
    "option4": "Fırtına",
    "correctAnswer": 2,
    "difficulty": "hard",
    "explanation": "Doğu Anadolu gibi yüksek yerlerde kar kütlelerinin düşmesi çığ afetidir.",
    "theme": "3. Ünite: İnsanlar, Yerler ve Çevreler"
  },
  {
    "grade": 5,
    "subject": "Sosyal Bilgiler",
    "unit": "3. Ünite: İnsanlar, Yerler ve Çevreler",
    "question": "Yağış alan eğimli arazilerde, toprağın üst katmanının su ve rüzgarla yavaşça süpürülüp kel kalmasına ne ad verilir?",
    "option1": "Heyelan",
    "option2": "Erozyon (Aşınım)",
    "option3": "Deprem",
    "option4": "Çığ",
    "correctAnswer": 1,
    "difficulty": "hard",
    "explanation": "Ormanların yok olması erozyona zemin hazırlar, toprağı verimsizleştirir.",
    "theme": "3. Ünite: İnsanlar, Yerler ve Çevreler"
  },
  {
    "grade": 5,
    "subject": "Sosyal Bilgiler",
    "unit": "3. Ünite: İnsanlar, Yerler ve Çevreler",
    "question": "Nüfusun (insan sayısının) bir bölgede yoğun (kalabalık) olmasını sağlayan BEŞERİ etken hangisidir?",
    "option1": "İklimin ılıman olması",
    "option2": "Sanayi (fabrika) ve iş imkanlarının fazla olması",
    "option3": "Arazinin düz (ova) olması",
    "option4": "Su kaynaklarının bulunması",
    "correctAnswer": 1,
    "difficulty": "medium",
    "explanation": "A, C ve D şıkları doğal etkendir. Sanayi ve ticaret insan yapımı (beşeri) bir etkendir.",
    "theme": "3. Ünite: İnsanlar, Yerler ve Çevreler"
  },
  {
    "grade": 5,
    "subject": "Sosyal Bilgiler",
    "unit": "3. Ünite: İnsanlar, Yerler ve Çevreler",
    "question": "Ülkemizde nüfusu en kalabalık ve sanayisi en gelişmiş bölge neresidir?",
    "option1": "Marmara Bölgesi",
    "option2": "Doğu Anadolu Bölgesi",
    "option3": "Karadeniz Bölgesi",
    "option4": "İç Anadolu Bölgesi",
    "correctAnswer": 0,
    "difficulty": "easy",
    "explanation": "İstanbul ve çevresi sanayi, ticaret ve ulaşım ağından dolayı en kalabalık yerdir.",
    "theme": "3. Ünite: İnsanlar, Yerler ve Çevreler"
  },
  {
    "grade": 5,
    "subject": "Sosyal Bilgiler",
    "unit": "4. Ünite: Bilim, Teknoloji ve Toplum",
    "question": "Bilimsel araştırmalarda ilk yapılması gereken adım hangisidir?",
    "option1": "Bilgi toplamak",
    "option2": "Araştırma konusunu (Problemi) belirlemek",
    "option3": "Rapor yazmak",
    "option4": "Kaynakça oluşturmak",
    "correctAnswer": 1,
    "difficulty": "medium",
    "explanation": "Her araştırma önce neyin inceleneceğinin, yani konunun belirlenmesiyle başlar.",
    "theme": "4. Ünite: Bilim, Teknoloji ve Toplum"
  },
  {
    "grade": 5,
    "subject": "Sosyal Bilgiler",
    "unit": "4. Ünite: Bilim, Teknoloji ve Toplum",
    "question": "Bilgiye ulaşırken interneti güvenli ve doğru (medya okuryazarı olarak) kullanmak ne demektir?",
    "option1": "Her gördüğüne inanıp paylaşmak",
    "option2": "Bilgiyi sadece bir siteden almak",
    "option3": "İnternet haberlerini farklı ve güvenilir resmi (gov, edu) sitelerden doğrulamak",
    "option4": "İnternette kendi özel şifrelerimizi yaymak",
    "correctAnswer": 2,
    "difficulty": "easy",
    "explanation": "İnternette bilgi kirliliği vardır, doğru bilgi farklı yerlerden teyit edilmelidir.",
    "theme": "4. Ünite: Bilim, Teknoloji ve Toplum"
  },
  {
    "grade": 5,
    "subject": "Sosyal Bilgiler",
    "unit": "4. Ünite: Bilim, Teknoloji ve Toplum",
    "question": "İnternet ortamında kendi kimliğimizi ve özel bilgilerimizi korumaya ne ad verilir?",
    "option1": "Siber (Dijital) güvenlik",
    "option2": "Fiziksel şiddet",
    "option3": "Haberleşme özgürlüğü",
    "option4": "Kronoloji",
    "correctAnswer": 0,
    "difficulty": "medium",
    "explanation": "Bilgisayar korsanlarına karşı dijital alanımızı koruma işlemine siber güvenlik denir.",
    "theme": "4. Ünite: Bilim, Teknoloji ve Toplum"
  },
  {
    "grade": 5,
    "subject": "Sosyal Bilgiler",
    "unit": "4. Ünite: Bilim, Teknoloji ve Toplum",
    "question": "Araştırma sonunda ödevimize yararlandığımız kitap veya sitelerin listesini yazdığımız bölüme ne denir?",
    "option1": "Giriş",
    "option2": "Kaynakça",
    "option3": "Fihrist",
    "option4": "İçindekiler",
    "correctAnswer": 1,
    "difficulty": "easy",
    "explanation": "Emeğe saygı göstermek için bilgiyi aldığımız yerler kaynakçada belirtilir.",
    "theme": "4. Ünite: Bilim, Teknoloji ve Toplum"
  },
  {
    "grade": 5,
    "subject": "Sosyal Bilgiler",
    "unit": "4. Ünite: Bilim, Teknoloji ve Toplum",
    "question": "Başkalarına ait eserleri, fikirleri veya yazıları kendimizinmiş gibi izinsiz kopyalamak hangi hakkın ihlalidir?",
    "option1": "Yaşama hakkı",
    "option2": "Eser sahibinin 'Telif (Fikir) Hakkı'",
    "option3": "Seyahat hakkı",
    "option4": "Eğitim hakkı",
    "correctAnswer": 1,
    "difficulty": "hard",
    "explanation": "Emek vererek eser üretenlerin hukuki hakkı Telif Hakkıdır.",
    "theme": "4. Ünite: Bilim, Teknoloji ve Toplum"
  },
  {
    "grade": 5,
    "subject": "Sosyal Bilgiler",
    "unit": "4. Ünite: Bilim, Teknoloji ve Toplum",
    "question": "İnternet uzantılarında üniversitelere ve eğitim kurumlarına ait olan ve güvenilir bilgi sunan uzantı hangisidir?",
    "option1": ".com",
    "option2": ".org",
    "option3": ".edu",
    "option4": ".net",
    "correctAnswer": 2,
    "difficulty": "medium",
    "explanation": "'Edu' (Education), üniversitelerin kullandığı resmi uzantıdır.",
    "theme": "4. Ünite: Bilim, Teknoloji ve Toplum"
  },
  {
    "grade": 5,
    "subject": "Sosyal Bilgiler",
    "unit": "4. Ünite: Bilim, Teknoloji ve Toplum",
    "question": "Teknolojinin sosyal hayata OLUmsuz bir etkisi hangisidir?",
    "option1": "İletişimi hızlandırması",
    "option2": "Tedavileri kolaylaştırması",
    "option3": "Aile içi iletişimi ve yüz yüze sohbeti azaltması",
    "option4": "Bilgiye erişimi kolaylaştırması",
    "correctAnswer": 2,
    "difficulty": "easy",
    "explanation": "Telefon ve bilgisayar bağımlılığı insanların sosyalleşmesini engeller.",
    "theme": "4. Ünite: Bilim, Teknoloji ve Toplum"
  },
  {
    "grade": 5,
    "subject": "Sosyal Bilgiler",
    "unit": "4. Ünite: Bilim, Teknoloji ve Toplum",
    "question": "Bir mucit icat yaparken hangi özelliğe sahip olmalıdır?",
    "option1": "Meraklı, sabırlı ve gözlemci olmalıdır",
    "option2": "Çabuk pes etmelidir",
    "option3": "Başkalarının fikrini kopyalamalıdır",
    "option4": "Hiç hata yapmamalıdır",
    "correctAnswer": 0,
    "difficulty": "easy",
    "explanation": "Bilim insanları meraklı, azimli ve objektif kişilerdir.",
    "theme": "4. Ünite: Bilim, Teknoloji ve Toplum"
  },
  {
    "grade": 5,
    "subject": "Sosyal Bilgiler",
    "unit": "4. Ünite: Bilim, Teknoloji ve Toplum",
    "question": "Teknolojinin gelişmesiyle icat edilen E-Devlet kapısı vatandaşlara ne kolaylık sağlar?",
    "option1": "Oyun oynamayı sağlar",
    "option2": "Devlet dairelerine gitmeden resmi belgeleri evden hızlıca almayı sağlar",
    "option3": "Para basmayı sağlar",
    "option4": "Sadece haber okutur",
    "correctAnswer": 1,
    "difficulty": "medium",
    "explanation": "E-devlet şifresiyle ikametgah, belge gibi işlemler internetten sıra beklemeden çözülür.",
    "theme": "4. Ünite: Bilim, Teknoloji ve Toplum"
  },
  {
    "grade": 5,
    "subject": "Sosyal Bilgiler",
    "unit": "4. Ünite: Bilim, Teknoloji ve Toplum",
    "question": "Sanal zorbalık veya dolandırıcılıkla karşılaştığımızda ne yapmalıyız?",
    "option1": "Ailemize veya polise (siber suçlar birimine) haber vermeliyiz",
    "option2": "Korkup sessiz kalmalıyız",
    "option3": "Parayı ödeyip kurtulmalıyız",
    "option4": "Biz de onlara saldırmalıyız",
    "correctAnswer": 0,
    "difficulty": "hard",
    "explanation": "İnternet suçlarında mutlaka yetişkinlere ve resmi mercilere bilgi verilmelidir.",
    "theme": "4. Ünite: Bilim, Teknoloji ve Toplum"
  },
  {
    "grade": 5,
    "subject": "Sosyal Bilgiler",
    "unit": "5. Ünite: Üretim, Dağıtım ve Tüketim",
    "question": "Toprağı ekip biçerek ürün elde etme faaliyetine ne ad verilir?",
    "option1": "Hayvancılık",
    "option2": "Turizm",
    "option3": "Tarım",
    "option4": "Sanayi",
    "correctAnswer": 2,
    "difficulty": "easy",
    "explanation": "Buğday, pamuk gibi bitkilerin tarlada yetiştirilmesi tarımsal ekonomik faaliyettir.",
    "theme": "5. Ünite: Üretim, Dağıtım ve Tüketim"
  },
  {
    "grade": 5,
    "subject": "Sosyal Bilgiler",
    "unit": "5. Ünite: Üretim, Dağıtım ve Tüketim",
    "question": "Doğudaki geniş meralarda ve dağlık alanlarda insanların en çok yaptığı ekonomik faaliyet nedir?",
    "option1": "Turizm",
    "option2": "Sanayi",
    "option3": "Büyükbaş hayvancılık",
    "option4": "Denizcilik",
    "correctAnswer": 2,
    "difficulty": "medium",
    "explanation": "Erzurum-Kars gibi çayırların bol ve arazinin dağlık olduğu yerlerde hayvancılık gelişir.",
    "theme": "5. Ünite: Üretim, Dağıtım ve Tüketim"
  },
  {
    "grade": 5,
    "subject": "Sosyal Bilgiler",
    "unit": "5. Ünite: Üretim, Dağıtım ve Tüketim",
    "question": "Hammaddelerin fabrikalarda işlenerek yeni ürünlere dönüştürülmesine ne ad verilir?",
    "option1": "Tarım",
    "option2": "Sanayi (Endüstri)",
    "option3": "Madencilik",
    "option4": "Dağıtım",
    "correctAnswer": 1,
    "difficulty": "medium",
    "explanation": "Fabrikalarda makine gücüyle pamuğun kazağa, demirin arabaya dönüşmesi sanayidir.",
    "theme": "5. Ünite: Üretim, Dağıtım ve Tüketim"
  },
  {
    "grade": 5,
    "subject": "Sosyal Bilgiler",
    "unit": "5. Ünite: Üretim, Dağıtım ve Tüketim",
    "question": "Yaz aylarında Antalya ve Muğla gibi kıyı illerinde en çok gelir getiren ekonomik sektör hangisidir?",
    "option1": "Ormancılık",
    "option2": "Turizm",
    "option3": "Madencilik",
    "option4": "Bilişim",
    "correctAnswer": 1,
    "difficulty": "easy",
    "explanation": "Sıcak iklim ve deniz nedeniyle Akdeniz kıyılarında otelcilik ve turizm gelişmiştir.",
    "theme": "5. Ünite: Üretim, Dağıtım ve Tüketim"
  },
  {
    "grade": 5,
    "subject": "Sosyal Bilgiler",
    "unit": "5. Ünite: Üretim, Dağıtım ve Tüketim",
    "question": "Bir ürünün fabrikada üretildikten sonra marketlere tırlarla taşınması hangi aşamadır?",
    "option1": "Tüketim",
    "option2": "Dağıtım",
    "option3": "Üretim",
    "option4": "Geri dönüşüm",
    "correctAnswer": 1,
    "difficulty": "easy",
    "explanation": "Ürünün fabrikadan alınıp satılacağı yerlere nakledilmesi dağıtımdır.",
    "theme": "5. Ünite: Üretim, Dağıtım ve Tüketim"
  },
  {
    "grade": 5,
    "subject": "Sosyal Bilgiler",
    "unit": "5. Ünite: Üretim, Dağıtım ve Tüketim",
    "question": "Yenilikçi, risk alan ve piyasada olmayan yeni bir iş kuran kişilere ne ad verilir?",
    "option1": "Memur",
    "option2": "Girişimci",
    "option3": "Öğrenci",
    "option4": "İşçi",
    "correctAnswer": 1,
    "difficulty": "hard",
    "explanation": "Girişimci, yeni bir fikir bulup üretime döken ve istihdam sağlayan kişidir.",
    "theme": "5. Ünite: Üretim, Dağıtım ve Tüketim"
  },
  {
    "grade": 5,
    "subject": "Sosyal Bilgiler",
    "unit": "5. Ünite: Üretim, Dağıtım ve Tüketim",
    "question": "İnsanların temel ihtiyaçlarını karşılayan meslekler her zaman vardır. Buna göre Karadeniz kıyılarında yaygın olan meslek nedir?",
    "option1": "Pamuk tarımı",
    "option2": "Balıkçılık ve ormancılık",
    "option3": "Turist rehberliği",
    "option4": "Bankacılık",
    "correctAnswer": 1,
    "difficulty": "medium",
    "explanation": "Karadeniz'de denizin verimi balıkçılığı, sık ormanlar ise ormancılığı geliştirmiştir.",
    "theme": "5. Ünite: Üretim, Dağıtım ve Tüketim"
  },
  {
    "grade": 5,
    "subject": "Sosyal Bilgiler",
    "unit": "5. Ünite: Üretim, Dağıtım ve Tüketim",
    "question": "Bilinçli bir tüketici alışveriş yaparken neye dikkat eder?",
    "option1": "İhtiyacı olmayanları alır",
    "option2": "Fişini almaz",
    "option3": "İhtiyaçlarına öncelik verir, TSE damgası ve SKT'ye bakar",
    "option4": "Sadece reklamlarda çıkanı alır",
    "correctAnswer": 2,
    "difficulty": "easy",
    "explanation": "Bilinçli tüketici önce ihtiyaçlarını belirler, kalite kontrolü yapar ve belgesini alır.",
    "theme": "5. Ünite: Üretim, Dağıtım ve Tüketim"
  },
  {
    "grade": 5,
    "subject": "Sosyal Bilgiler",
    "unit": "5. Ünite: Üretim, Dağıtım ve Tüketim",
    "question": "Bir kişi ayakkabı aldıktan sonra yırtık olduğunu fark ederse ilk olarak ne yapmalıdır?",
    "option1": "Çöpe atmalıdır",
    "option2": "Fişi ile birlikte satıcıya gidip değişim/iade talep etmelidir",
    "option3": "Terziye vermelidir",
    "option4": "Polis çağırmalıdır",
    "correctAnswer": 1,
    "difficulty": "medium",
    "explanation": "Ayıplı/kusurlu mallar garanti belgesi ve fiş ile satıcıdan değiştirilmelidir.",
    "theme": "5. Ünite: Üretim, Dağıtım ve Tüketim"
  },
  {
    "grade": 5,
    "subject": "Sosyal Bilgiler",
    "unit": "5. Ünite: Üretim, Dağıtım ve Tüketim",
    "question": "Ailemizin bir aylık parasının (gelir) nereye harcanacağının (gider) listesinin yapılmasına ne ad verilir?",
    "option1": "Kumbara",
    "option2": "Banka",
    "option3": "Bütçe planlaması",
    "option4": "Vergi",
    "correctAnswer": 2,
    "difficulty": "easy",
    "explanation": "Gelir ve giderlerin dengeleme tablosu bütçedir.",
    "theme": "5. Ünite: Üretim, Dağıtım ve Tüketim"
  },
  {
    "grade": 5,
    "subject": "Sosyal Bilgiler",
    "unit": "6. Ünite: Etkin Vatandaşlık",
    "question": "Ülkemizde halka hizmet eden devlet hastanesi, okul, polis karakolu gibi kurumlara ne ad verilir?",
    "option1": "Resmi (Kamu) Kurum",
    "option2": "Sivil Toplum Kuruluşu (STK)",
    "option3": "Fabrika",
    "option4": "Market",
    "correctAnswer": 0,
    "difficulty": "easy",
    "explanation": "Devletin vatandaşına hizmet etmek için açtığı ücretsiz veya resmi yerler resmi kurumlardır.",
    "theme": "6. Ünite: Etkin Vatandaşlık"
  },
  {
    "grade": 5,
    "subject": "Sosyal Bilgiler",
    "unit": "6. Ünite: Etkin Vatandaşlık",
    "question": "Gönüllü kişilerin maaş beklemeden topluma yardım etmek için kurdukları (Örn: LÖSEV, TEMA) yerlere ne denir?",
    "option1": "Hastane",
    "option2": "Resmi Kurum",
    "option3": "Sivil Toplum Kuruluşu (STK)",
    "option4": "Bakanlık",
    "correctAnswer": 2,
    "difficulty": "medium",
    "explanation": "Dernekler ve vakıflar gönüllülük esasıyla çalışan Sivil Toplum Kuruluşlarıdır.",
    "theme": "6. Ünite: Etkin Vatandaşlık"
  },
  {
    "grade": 5,
    "subject": "Sosyal Bilgiler",
    "unit": "6. Ünite: Etkin Vatandaşlık",
    "question": "Çevrenin korunması ve ağaçlandırma faaliyetleri yürüten ünlü Sivil Toplum Kuruluşu hangisidir?",
    "option1": "Kızılay",
    "option2": "TEMA Vakfı",
    "option3": "Yeşilay",
    "option4": "AKUT",
    "correctAnswer": 1,
    "difficulty": "easy",
    "explanation": "Türkiye Erozyonla Mücadele ve Ağaçlandırma Vakfı (TEMA) doğayı korur.",
    "theme": "6. Ünite: Etkin Vatandaşlık"
  },
  {
    "grade": 5,
    "subject": "Sosyal Bilgiler",
    "unit": "6. Ünite: Etkin Vatandaşlık",
    "question": "Vatandaşların, devlet hizmetleri için kazançları oranında devlete ödediği paraya ne denir?",
    "option1": "Bağış",
    "option2": "Fatura",
    "option3": "Vergi",
    "option4": "Maaş",
    "correctAnswer": 2,
    "difficulty": "easy",
    "explanation": "Devlet, yollar ve hastaneler yapmak için vatandaşlardan yasal Vergi toplar.",
    "theme": "6. Ünite: Etkin Vatandaşlık"
  },
  {
    "grade": 5,
    "subject": "Sosyal Bilgiler",
    "unit": "6. Ünite: Etkin Vatandaşlık",
    "question": "Merkezi yönetimde devletin yürütme gücünün başında kim bulunur?",
    "option1": "Muhtar",
    "option2": "Cumhurbaşkanı",
    "option3": "Vali",
    "option4": "Belediye Başkanı",
    "correctAnswer": 1,
    "difficulty": "medium",
    "explanation": "Ülkemizde yürütme yetkisi ve görevi Cumhurbaşkanı'na aittir.",
    "theme": "6. Ünite: Etkin Vatandaşlık"
  },
  {
    "grade": 5,
    "subject": "Sosyal Bilgiler",
    "unit": "6. Ünite: Etkin Vatandaşlık",
    "question": "İllerde devleti ve Cumhurbaşkanı'nı temsil eden en yüksek mülki amir kimdir?",
    "option1": "Kaymakam",
    "option2": "Bakan",
    "option3": "Vali",
    "option4": "Muhtar",
    "correctAnswer": 2,
    "difficulty": "medium",
    "explanation": "İllerde yönetimin başında Vali bulunur, ilçelerde ise Kaymakam.",
    "theme": "6. Ünite: Etkin Vatandaşlık"
  },
  {
    "grade": 5,
    "subject": "Sosyal Bilgiler",
    "unit": "6. Ünite: Etkin Vatandaşlık",
    "question": "Yerel seçimlerle (halkın oyuyla) başa gelerek şehrin temizlik, yol, su gibi ihtiyaçlarını çözen kurum hangisidir?",
    "option1": "Valilik",
    "option2": "Belediye",
    "option3": "Kaymakamlık",
    "option4": "Karakol",
    "correctAnswer": 1,
    "difficulty": "hard",
    "explanation": "Belediyeler yerel yönetim birimidir ve başkanları halkın oyuyla seçilir.",
    "theme": "6. Ünite: Etkin Vatandaşlık"
  },
  {
    "grade": 5,
    "subject": "Sosyal Bilgiler",
    "unit": "6. Ünite: Etkin Vatandaşlık",
    "question": "Toplumda huzurla yaşayabilmek için katıldığımız etkinliklerde nasıl davranmalıyız?",
    "option1": "Bencil ve saygısız",
    "option2": "Demokratik, kurallara uyan ve katılımcı",
    "option3": "Kavgacı",
    "option4": "Şiddet yanlısı",
    "correctAnswer": 1,
    "difficulty": "easy",
    "explanation": "İyi bir vatandaş toplumsal kurallara ve demokratik değerlere uyar.",
    "theme": "6. Ünite: Etkin Vatandaşlık"
  },
  {
    "grade": 5,
    "subject": "Sosyal Bilgiler",
    "unit": "6. Ünite: Etkin Vatandaşlık",
    "question": "Temel haklarımızı kullanabilmek için en başta hangi hakka sahip olmamız gerekir?",
    "option1": "Yaşama Hakkı",
    "option2": "Oyun Hakkı",
    "option3": "Çalışma Hakkı",
    "option4": "Dinlenme Hakkı",
    "correctAnswer": 0,
    "difficulty": "medium",
    "explanation": "Diğer tüm hakların var olabilmesi için insanın hayatta olması (yaşama hakkı) şarttır.",
    "theme": "6. Ünite: Etkin Vatandaşlık"
  },
  {
    "grade": 5,
    "subject": "Sosyal Bilgiler",
    "unit": "6. Ünite: Etkin Vatandaşlık",
    "question": "Afetlerde (deprem, sel) çadır ve kan yardımı yaparak yaraları saran Kızılay, hangi tür bir kurum örneğidir?",
    "option1": "Fabrika",
    "option2": "Ticari şirket",
    "option3": "Resmi Kurum ve STK işbirliğiyle çalışan insani yardım kurumu",
    "option4": "Okul",
    "correctAnswer": 2,
    "difficulty": "hard",
    "explanation": "Kızılay, toplumun bağışlarıyla yürüyen en büyük insani yardım sivil inisiyatiflerindendir.",
    "theme": "6. Ünite: Etkin Vatandaşlık"
  },
  {
    "grade": 5,
    "subject": "Sosyal Bilgiler",
    "unit": "7. Ünite: Küresel Bağlantılar",
    "question": "Bir ülkenin ürettiği malları başka ülkelere SATMASINA ne denir?",
    "option1": "İthalat",
    "option2": "İhracat (Dış Satım)",
    "option3": "Turizm",
    "option4": "Enflasyon",
    "correctAnswer": 1,
    "difficulty": "medium",
    "explanation": "Fazla veya kıymetli malların yurtdışına satılmasına İhracat denir.",
    "theme": "7. Ünite: Küresel Bağlantılar"
  },
  {
    "grade": 5,
    "subject": "Sosyal Bilgiler",
    "unit": "7. Ünite: Küresel Bağlantılar",
    "question": "Bir ülkenin ihtiyacı olan malları başka ülkelerden ALMASINA ne denir?",
    "option1": "İthalat (Dış Alım)",
    "option2": "İhracat",
    "option3": "Üretim",
    "option4": "Kültür",
    "correctAnswer": 0,
    "difficulty": "medium",
    "explanation": "Petrol, doğalgaz gibi dışarıdan para verilerek alınan mallar ithalattır.",
    "theme": "7. Ünite: Küresel Bağlantılar"
  },
  {
    "grade": 5,
    "subject": "Sosyal Bilgiler",
    "unit": "7. Ünite: Küresel Bağlantılar",
    "question": "Turizmin bir ülkeye ekonomik faydası nedir?",
    "option1": "Çevre kirliliğini artırır",
    "option2": "Döviz (yabancı para) kazandırarak ülke ekonomisini güçlendirir",
    "option3": "Tarımı bitirir",
    "option4": "Ülkeyi fakirleştirir",
    "correctAnswer": 1,
    "difficulty": "easy",
    "explanation": "Turistler (misafirler) ülkemizde döviz bırakarak (Bacasız Sanayi) ekonomiye katkı sağlarlar.",
    "theme": "7. Ünite: Küresel Bağlantılar"
  },
  {
    "grade": 5,
    "subject": "Sosyal Bilgiler",
    "unit": "7. Ünite: Küresel Bağlantılar",
    "question": "Türkiye'nin Asya, Avrupa ve Afrika kıtalarının birbirine en yakın olduğu yerde bulunması neyi gösterir?",
    "option1": "Nüfusunu",
    "option2": "Jeopolitik (Coğrafi) konumunun önemini",
    "option3": "Gelişmişliğini",
    "option4": "İklimini",
    "correctAnswer": 1,
    "difficulty": "hard",
    "explanation": "Ülkemiz kıtalar arası köprü görevindedir, bu stratejik ve coğrafi bir güçtür.",
    "theme": "7. Ünite: Küresel Bağlantılar"
  },
  {
    "grade": 5,
    "subject": "Sosyal Bilgiler",
    "unit": "7. Ünite: Küresel Bağlantılar",
    "question": "Hangi komşu ülke ile aramızda en uzun sınır kapıları bulunmaktadır?",
    "option1": "Yunanistan",
    "option2": "Suriye",
    "option3": "İran",
    "option4": "Gürcistan",
    "correctAnswer": 1,
    "difficulty": "hard",
    "explanation": "Türkiye'nin en uzun kara sınırı güneydeki komşusu Suriye iledir.",
    "theme": "7. Ünite: Küresel Bağlantılar"
  },
  {
    "grade": 5,
    "subject": "Sosyal Bilgiler",
    "unit": "7. Ünite: Küresel Bağlantılar",
    "question": "Dünya üzerindeki tüm insanların barış ve huzur içinde yaşayabilmesi için hangisine ihtiyaç vardır?",
    "option1": "Savaşlara",
    "option2": "Sınırların kapanmasına",
    "option3": "Karşılıklı hoşgörü, saygı ve uluslararası işbirliğine",
    "option4": "Sadece zengin olmaya",
    "correctAnswer": 2,
    "difficulty": "easy",
    "explanation": "Farklı kültürlere saygı duymak küresel barışın anahtarıdır.",
    "theme": "7. Ünite: Küresel Bağlantılar"
  },
  {
    "grade": 5,
    "subject": "Sosyal Bilgiler",
    "unit": "7. Ünite: Küresel Bağlantılar",
    "question": "Gelişen ulaşım (uçak) ve iletişim (internet) araçları dünyayı nasıl etkilemiştir?",
    "option1": "Ülkeleri birbirinden uzaklaştırmıştır",
    "option2": "Kültürel etkileşimi artırarak dünyayı küçük bir köy haline getirmiştir",
    "option3": "Ticareti bitirmiştir",
    "option4": "Bilimsel gelişmeleri durdurmuştur",
    "correctAnswer": 1,
    "difficulty": "medium",
    "explanation": "Mesafelerin kısalmasıyla küresel bağlar hızlanmış, etkileşim artmıştır.",
    "theme": "7. Ünite: Küresel Bağlantılar"
  },
  {
    "grade": 5,
    "subject": "Sosyal Bilgiler",
    "unit": "7. Ünite: Küresel Bağlantılar",
    "question": "Aşağıdakilerden hangisi Türkiye'nin dünyaya sattığı (ihraç ettiği) ürünlerden biridir?",
    "option1": "Fındık, incir, tekstil ürünleri",
    "option2": "Doğalgaz ve petrol",
    "option3": "Tropikal meyveler (muz, ananas)",
    "option4": "Uzay mekikleri",
    "correctAnswer": 0,
    "difficulty": "medium",
    "explanation": "Tarım ürünleri (fındık, kayısı, incir) ve tekstil ülkemizin önemli ihracat kalemleridir.",
    "theme": "7. Ünite: Küresel Bağlantılar"
  },
  {
    "grade": 5,
    "subject": "Sosyal Bilgiler",
    "unit": "7. Ünite: Küresel Bağlantılar",
    "question": "Eski çağlarda Çin'den başlayıp Avrupa'ya kadar giden ve ülkemizden geçen tarihi ticaret yolu hangisidir?",
    "option1": "Baharat Yolu",
    "option2": "İpek Yolu",
    "option3": "Kral Yolu",
    "option4": "Göç Yolu",
    "correctAnswer": 1,
    "difficulty": "hard",
    "explanation": "İpeğin taşındığı tarihi ve küresel ticaret yolu İpek Yoludur.",
    "theme": "7. Ünite: Küresel Bağlantılar"
  },
  {
    "grade": 5,
    "subject": "Sosyal Bilgiler",
    "unit": "7. Ünite: Küresel Bağlantılar",
    "question": "Dünya genelindeki tarihi eserleri ve doğal güzellikleri (Kapadokya, Mısır Piramitleri) koruyan Birleşmiş Milletler kurumu hangisidir?",
    "option1": "Kırmızı Hilal",
    "option2": "UNICEF",
    "option3": "UNESCO",
    "option4": "Kızılay",
    "correctAnswer": 2,
    "difficulty": "medium",
    "explanation": "Dünyadaki önemli tarihi eserleri ve doğal güzellikleri 'Dünya Mirası' listesine alarak koruyan Birleşmiş Milletler kurumu UNESCO'dur.",
    "theme": "7. Ünite: Küresel Bağlantılar"
  }
]