[
  {
    "grade": 6,
    "subject": "Fen Bilimleri",
    "unit": "1. Ünite: Güneş Sistemi ve Tutulmalar",
    "question": "Güneş sistemindeki en büyük gezegen aşağıdakilerden hangisidir?",
    "option1": "Dünya",
    "option2": "Jüpiter",
    "option3": "Satürn",
    "option4": "Mars",
    "correctAnswer": 1,
    "difficulty": "easy",
    "explanation": "Gazsal bir dev olan Jüpiter, güneş sisteminin en büyük gezegenidir.",
    "theme": "1. Ünite: Güneş Sistemi ve Tutulmalar"
  },
  {
    "grade": 6,
    "subject": "Fen Bilimleri",
    "unit": "1. Ünite: Güneş Sistemi ve Tutulmalar",
    "question": "Karasal (İç) gezegenlerin en küçüğü ve Güneş'e en yakın olanı hangisidir?",
    "option1": "Venüs",
    "option2": "Merkür",
    "option3": "Dünya",
    "option4": "Mars",
    "correctAnswer": 1,
    "difficulty": "easy",
    "explanation": "Merkür Güneşe en yakın ve aynı zamanda en küçük gezegendir.",
    "theme": "1. Ünite: Güneş Sistemi ve Tutulmalar"
  },
  {
    "grade": 6,
    "subject": "Fen Bilimleri",
    "unit": "1. Ünite: Güneş Sistemi ve Tutulmalar",
    "question": "Etrafında çok belirgin buz ve kaya parçalarından oluşan 'halkaları' bulunan gezegen hangisidir?",
    "option1": "Uranüs",
    "option2": "Neptün",
    "option3": "Jüpiter",
    "option4": "Satürn",
    "correctAnswer": 3,
    "difficulty": "easy",
    "explanation": "Satürn, belirgin toz ve buz halkalarıyla tanınan gazsal bir gezegendir.",
    "theme": "1. Ünite: Güneş Sistemi ve Tutulmalar"
  },
  {
    "grade": 6,
    "subject": "Fen Bilimleri",
    "unit": "1. Ünite: Güneş Sistemi ve Tutulmalar",
    "question": "Mars ile Jüpiter arasında yer alan ve gezegen olamamış kaya parçalarının oluşturduğu kuşağa ne denir?",
    "option1": "Samanyolu",
    "option2": "Asteroit kuşağı",
    "option3": "Kuyruklu yıldız",
    "option4": "Meteor",
    "correctAnswer": 1,
    "difficulty": "medium",
    "explanation": "İç ve dış gezegenleri birbirinden ayıran sınıra asteroit kuşağı denir.",
    "theme": "1. Ünite: Güneş Sistemi ve Tutulmalar"
  },
  {
    "grade": 6,
    "subject": "Fen Bilimleri",
    "unit": "1. Ünite: Güneş Sistemi ve Tutulmalar",
    "question": "Atmosfere girip sürtünmeden dolayı yanarak ışık saçan meteorlara halk arasında ne ad verilir?",
    "option1": "UFO",
    "option2": "Uydular",
    "option3": "Yıldız kayması",
    "option4": "Asteroit",
    "correctAnswer": 2,
    "difficulty": "easy",
    "explanation": "Gerçekte yıldız olmayan bu yanan göktaşları yıldız kayması olarak bilinir.",
    "theme": "1. Ünite: Güneş Sistemi ve Tutulmalar"
  },
  {
    "grade": 6,
    "subject": "Fen Bilimleri",
    "unit": "1. Ünite: Güneş Sistemi ve Tutulmalar",
    "question": "Ay, Güneş ile Dünya arasına girip Güneş ışığını engellediğinde hangi doğa olayı gerçekleşir?",
    "option1": "Ay Tutulması",
    "option2": "Güneş Tutulması",
    "option3": "Dolunay",
    "option4": "Mevsim değişimi",
    "correctAnswer": 1,
    "difficulty": "medium",
    "explanation": "Ay araya girdiğinde Dünya'nın bir kısmı gündüz vakti kararır, buna Güneş tutulması denir.",
    "theme": "1. Ünite: Güneş Sistemi ve Tutulmalar"
  },
  {
    "grade": 6,
    "subject": "Fen Bilimleri",
    "unit": "1. Ünite: Güneş Sistemi ve Tutulmalar",
    "question": "Ay tutulması sırasında gök cisimlerinin sıralanışı nasıldır?",
    "option1": "Güneş - Ay - Dünya",
    "option2": "Dünya - Güneş - Ay",
    "option3": "Ay - Güneş - Dünya",
    "option4": "Güneş - Dünya - Ay",
    "correctAnswer": 3,
    "difficulty": "medium",
    "explanation": "Dünya araya girer ve Ay, Dünya'nın gölgesinde kalır.",
    "theme": "1. Ünite: Güneş Sistemi ve Tutulmalar"
  },
  {
    "grade": 6,
    "subject": "Fen Bilimleri",
    "unit": "1. Ünite: Güneş Sistemi ve Tutulmalar",
    "question": "Güneş sistemindeki en sıcak gezegen, atmosferindeki sera gazlarından dolayı hangisidir?",
    "option1": "Merkür",
    "option2": "Venüs",
    "option3": "Dünya",
    "option4": "Mars",
    "correctAnswer": 1,
    "difficulty": "hard",
    "explanation": "Merkür daha yakın olmasına rağmen, Venüs'ün kalın atmosferi sera etkisi yaratır ve onu en sıcak gezegen yapar.",
    "theme": "1. Ünite: Güneş Sistemi ve Tutulmalar"
  },
  {
    "grade": 6,
    "subject": "Fen Bilimleri",
    "unit": "1. Ünite: Güneş Sistemi ve Tutulmalar",
    "question": "Ay tutulması, Ay'ın hangi evresinde gerçekleşebilir?",
    "option1": "Yeni Ay",
    "option2": "İlk Dördün",
    "option3": "Dolunay",
    "option4": "Son Dördün",
    "correctAnswer": 2,
    "difficulty": "hard",
    "explanation": "Dünya ortadayken Ay tam karşıdadır, yani Dolunay evresindedir.",
    "theme": "1. Ünite: Güneş Sistemi ve Tutulmalar"
  },
  {
    "grade": 6,
    "subject": "Fen Bilimleri",
    "unit": "1. Ünite: Güneş Sistemi ve Tutulmalar",
    "question": "Hem Güneş hem de Ay tutulmasının ortak özelliği nedir?",
    "option1": "İkisi de gece gözlenir.",
    "option2": "Işığın doğrusal yayıldığını kanıtlar.",
    "option3": "Her ay gerçekleşir.",
    "option4": "İnsanlara zarar verir.",
    "correctAnswer": 1,
    "difficulty": "medium",
    "explanation": "Tutulmalar, ışığın dümdüz yayılarak opak cisimleri geçemeyip gölge oluşturması kuralına dayanır.",
    "theme": "1. Ünite: Güneş Sistemi ve Tutulmalar"
  },
  {
    "grade": 6,
    "subject": "Fen Bilimleri",
    "unit": "2. Ünite: Vücudumuzdaki Sistemler",
    "question": "Vücudumuza şekil veren ve iç organlarımızı koruyan sisteme ne denir?",
    "option1": "Sindirim sistemi",
    "option2": "Dolaşım sistemi",
    "option3": "Destek ve Hareket sistemi",
    "option4": "Solunum sistemi",
    "correctAnswer": 2,
    "difficulty": "easy",
    "explanation": "İskelet ve kaslarımızdan oluşan sistem destek ve hareket sistemidir.",
    "theme": "2. Ünite: Vücudumuzdaki Sistemler"
  },
  {
    "grade": 6,
    "subject": "Fen Bilimleri",
    "unit": "2. Ünite: Vücudumuzdaki Sistemler",
    "question": "Büyük besin maddelerinin enzimler (salgılar) yardımıyla hücrelere geçebilecek kadar küçültülmesine ne ad verilir?",
    "option1": "Fiziksel (Mekanik) sindirim",
    "option2": "Kimyasal sindirim",
    "option3": "Boşaltım",
    "option4": "Solunum",
    "correctAnswer": 1,
    "difficulty": "medium",
    "explanation": "Dişlerle yapılan mekanikken, tükürük veya mide özsuyu ile yapılan hücresel parçalama kimyasal sindirimdir.",
    "theme": "2. Ünite: Vücudumuzdaki Sistemler"
  },
  {
    "grade": 6,
    "subject": "Fen Bilimleri",
    "unit": "2. Ünite: Vücudumuzdaki Sistemler",
    "question": "Kimyasal sindirimin tamamen bittiği ve besinlerin kana karıştığı (emildiği) organ hangisidir?",
    "option1": "Mide",
    "option2": "Kalın bağırsak",
    "option3": "İnce bağırsak",
    "option4": "Ağız",
    "correctAnswer": 2,
    "difficulty": "medium",
    "explanation": "İnce bağırsaktaki villuslar sayesinde yararlı besinler kana geçer.",
    "theme": "2. Ünite: Vücudumuzdaki Sistemler"
  },
  {
    "grade": 6,
    "subject": "Fen Bilimleri",
    "unit": "2. Ünite: Vücudumuzdaki Sistemler",
    "question": "İsteğimiz dışında, sürekli ve ritmik olarak kasılan yorulmayan kas türü hangisidir?",
    "option1": "Çizgili kas",
    "option2": "Düz kas",
    "option3": "Kalp kası",
    "option4": "İskelet kası",
    "correctAnswer": 2,
    "difficulty": "easy",
    "explanation": "Kalp kası yapı olarak çizgili kasa, çalışma olarak düz kasa benzer ve ömür boyu yorulmaz.",
    "theme": "2. Ünite: Vücudumuzdaki Sistemler"
  },
  {
    "grade": 6,
    "subject": "Fen Bilimleri",
    "unit": "2. Ünite: Vücudumuzdaki Sistemler",
    "question": "Kanın vücuda pompalandığı kaslı organımız hangisidir?",
    "option1": "Karaciğer",
    "option2": "Kalp",
    "option3": "Akciğer",
    "option4": "Mide",
    "correctAnswer": 1,
    "difficulty": "easy",
    "explanation": "Dolaşım sisteminin merkezi olan kalp, kanı damarlara pompalar.",
    "theme": "2. Ünite: Vücudumuzdaki Sistemler"
  },
  {
    "grade": 6,
    "subject": "Fen Bilimleri",
    "unit": "2. Ünite: Vücudumuzdaki Sistemler",
    "question": "Vücudumuzu mikroplara karşı koruyan, asker gibi savunan kan hücreleri hangileridir?",
    "option1": "Alyuvarlar",
    "option2": "Kan pulçukları",
    "option3": "Akyuvarlar",
    "option4": "Plazma",
    "correctAnswer": 2,
    "difficulty": "medium",
    "explanation": "Akyuvarlar beyaz kan hücreleridir ve bağışıklık (savunma) sistemini oluştururlar.",
    "theme": "2. Ünite: Vücudumuzdaki Sistemler"
  },
  {
    "grade": 6,
    "subject": "Fen Bilimleri",
    "unit": "2. Ünite: Vücudumuzdaki Sistemler",
    "question": "Oksijence fakir (kirli) kanın kalpten çıkıp akciğerlere giderek temizlenip geri dönmesine ne ad verilir?",
    "option1": "Büyük kan dolaşımı",
    "option2": "Küçük kan dolaşımı",
    "option3": "Sindirim",
    "option4": "Boşaltım",
    "correctAnswer": 1,
    "difficulty": "hard",
    "explanation": "Kalp ve akciğer arasındaki bu kısa temizleme turuna küçük kan dolaşımı denir.",
    "theme": "2. Ünite: Vücudumuzdaki Sistemler"
  },
  {
    "grade": 6,
    "subject": "Fen Bilimleri",
    "unit": "2. Ünite: Vücudumuzdaki Sistemler",
    "question": "Kanımızdaki atık maddeleri (üre, ürik asit vb.) süzerek idrarı oluşturan organ hangisidir?",
    "option1": "Böbrekler",
    "option2": "Akciğer",
    "option3": "Deri",
    "option4": "Karaciğer",
    "correctAnswer": 0,
    "difficulty": "easy",
    "explanation": "Böbrekler kanın ana süzme ve temizleme tesisidir (Boşaltım sistemi).",
    "theme": "2. Ünite: Vücudumuzdaki Sistemler"
  },
  {
    "grade": 6,
    "subject": "Fen Bilimleri",
    "unit": "2. Ünite: Vücudumuzdaki Sistemler",
    "question": "Kafatasımızdaki kemiklerin arasındaki eklem türü hangisidir?",
    "option1": "Oynar eklem",
    "option2": "Yarı oynar eklem",
    "option3": "Oynamaz eklem",
    "option4": "Kaygan eklem",
    "correctAnswer": 2,
    "difficulty": "medium",
    "explanation": "Kafatası kemikleri birbirine testere dişi gibi sıkıca kilitlenmiştir, oynamazlar.",
    "theme": "2. Ünite: Vücudumuzdaki Sistemler"
  },
  {
    "grade": 6,
    "subject": "Fen Bilimleri",
    "unit": "2. Ünite: Vücudumuzdaki Sistemler",
    "question": "Akciğerin altında bulunan ve soluk alıp vermede kasılıp gevşeyerek göğüs boşluğunu ayarlayan kas hangisidir?",
    "option1": "Kalp",
    "option2": "Diyafram kası",
    "option3": "Pazı kası",
    "option4": "Mide kası",
    "correctAnswer": 1,
    "difficulty": "hard",
    "explanation": "Diyafram, solunum sistemine yardımcı olan yassı bir kastır.",
    "theme": "2. Ünite: Vücudumuzdaki Sistemler"
  },
  {
    "grade": 6,
    "subject": "Fen Bilimleri",
    "unit": "3. Ünite: Kuvvet ve Hareket",
    "question": "Aynı yönlü ve sırasıyla 5 N ve 7 N olan iki kuvvetin bileşkesi (Net kuvvet) kaç N'dur?",
    "option1": "2",
    "option2": "12",
    "option3": "35",
    "option4": "0",
    "correctAnswer": 1,
    "difficulty": "easy",
    "explanation": "Aynı yönlü kuvvetler toplanır. 5 + 7 = 12 N.",
    "theme": "3. Ünite: Kuvvet ve Hareket"
  },
  {
    "grade": 6,
    "subject": "Fen Bilimleri",
    "unit": "3. Ünite: Kuvvet ve Hareket",
    "question": "Zıt yönlü 10 N Batı'ya ve 6 N Doğu'ya uygulanan kuvvetlerin bileşkesi nasıldır?",
    "option1": "16 N Doğu",
    "option2": "4 N Batı",
    "option3": "4 N Doğu",
    "option4": "16 N Batı",
    "correctAnswer": 1,
    "difficulty": "medium",
    "explanation": "Zıt yönlü kuvvetler çıkarılır. 10 - 6 = 4 N. Büyük kuvvetin yönündedir (Batı).",
    "theme": "3. Ünite: Kuvvet ve Hareket"
  },
  {
    "grade": 6,
    "subject": "Fen Bilimleri",
    "unit": "3. Ünite: Kuvvet ve Hareket",
    "question": "Üzerine etki eden net kuvvet 0 (sıfır) ise bu cisim için ne söylenebilir?",
    "option1": "Kesinlikle hızlanır",
    "option2": "Dengelenmiş kuvvetlerin etkisindedir",
    "option3": "Yön değiştirir",
    "option4": "Dengelenmemiş kuvvet etkisindedir",
    "correctAnswer": 1,
    "difficulty": "medium",
    "explanation": "Net kuvvetin 0 olması, cismin dengede olduğunu (durduğunu veya sabit hızla gittiğini) gösterir.",
    "theme": "3. Ünite: Kuvvet ve Hareket"
  },
  {
    "grade": 6,
    "subject": "Fen Bilimleri",
    "unit": "3. Ünite: Kuvvet ve Hareket",
    "question": "Hareket halindeki bir otomobil frene basıp yavaşlıyorsa, hangi kuvvetin etkisindedir?",
    "option1": "Dengelenmiş kuvvet",
    "option2": "Bileşke kuvvet sıfırdır",
    "option3": "Dengelenmemiş kuvvet",
    "option4": "Hızlanan kuvvet",
    "correctAnswer": 2,
    "difficulty": "medium",
    "explanation": "Yavaşlayan veya hızlanan cisimlerin üzerindeki net kuvvet sıfır değildir, dengelenmemiştir.",
    "theme": "3. Ünite: Kuvvet ve Hareket"
  },
  {
    "grade": 6,
    "subject": "Fen Bilimleri",
    "unit": "3. Ünite: Kuvvet ve Hareket",
    "question": "Bir cismin aldığı yolun, geçen zamana bölünmesiyle (Yol ÷ Zaman) hangi büyüklük bulunur?",
    "option1": "Ağırlık",
    "option2": "Sürat",
    "option3": "Kuvvet",
    "option4": "Enerji",
    "correctAnswer": 1,
    "difficulty": "easy",
    "explanation": "Birim zamanda alınan yol 'Sürat'i verir.",
    "theme": "3. Ünite: Kuvvet ve Hareket"
  },
  {
    "grade": 6,
    "subject": "Fen Bilimleri",
    "unit": "3. Ünite: Kuvvet ve Hareket",
    "question": "Saatte 90 km (90 km/h) süratle giden bir otobüs, 3 saatte kaç km yol alır?",
    "option1": "30",
    "option2": "180",
    "option3": "270",
    "option4": "300",
    "correctAnswer": 2,
    "difficulty": "easy",
    "explanation": "Yol = Sürat x Zaman -> 90 x 3 = 270 km.",
    "theme": "3. Ünite: Kuvvet ve Hareket"
  },
  {
    "grade": 6,
    "subject": "Fen Bilimleri",
    "unit": "3. Ünite: Kuvvet ve Hareket",
    "question": "400 metrelik bir mesafeyi 20 saniyede koşan bir sporcunun sürati nedir?",
    "option1": "20 m/s",
    "option2": "80 m/s",
    "option3": "40 m/s",
    "option4": "10 m/s",
    "correctAnswer": 0,
    "difficulty": "medium",
    "explanation": "Sürat = Yol / Zaman -> 400 / 20 = 20 m/s.",
    "theme": "3. Ünite: Kuvvet ve Hareket"
  },
  {
    "grade": 6,
    "subject": "Fen Bilimleri",
    "unit": "3. Ünite: Kuvvet ve Hareket",
    "question": "Aynı mesafeyi (yolu) daha KISA sürede bitiren iki araçtan ikincisi için ne söylenebilir?",
    "option1": "Daha ağırdır",
    "option2": "Sürati daha azdır",
    "option3": "Sürati daha fazladır",
    "option4": "Geriye gitmiştir",
    "correctAnswer": 2,
    "difficulty": "medium",
    "explanation": "Aynı yolu kısa sürede tamamlayan araç daha hızlı (süratli) demektir.",
    "theme": "3. Ünite: Kuvvet ve Hareket"
  },
  {
    "grade": 6,
    "subject": "Fen Bilimleri",
    "unit": "3. Ünite: Kuvvet ve Hareket",
    "question": "Sürat-Zaman grafiği yatay düz bir çizgi olan hareketli için ne söylenir?",
    "option1": "Duruyordur",
    "option2": "Sabit süratle (eşit hızla) ilerliyordur",
    "option3": "Hızlanıyordur",
    "option4": "Yavaşlıyordur",
    "correctAnswer": 1,
    "difficulty": "hard",
    "explanation": "Zaman geçtikçe sürat değeri değişmiyor (yatay düz çizgi) ise sürat sabittir.",
    "theme": "3. Ünite: Kuvvet ve Hareket"
  },
  {
    "grade": 6,
    "subject": "Fen Bilimleri",
    "unit": "3. Ünite: Kuvvet ve Hareket",
    "question": "Masada duran bir vazoyu itmek için uygulanan kuvvetin hangi özelliği YOKTUR?",
    "option1": "Yönü",
    "option2": "Büyüklüğü (Şiddeti)",
    "option3": "Doğrultusu",
    "option4": "Rengi",
    "correctAnswer": 3,
    "difficulty": "easy",
    "explanation": "Kuvvetin yönü, doğrultusu, büyüklüğü ve uygulama noktası vardır ancak rengi yoktur.",
    "theme": "3. Ünite: Kuvvet ve Hareket"
  },
  {
    "grade": 6,
    "subject": "Fen Bilimleri",
    "unit": "4. Ünite: Madde ve Isı",
    "question": "Bütün maddeleri oluşturan, maddenin en küçük, gözle görülmez yapı taşlarına ne denir?",
    "option1": "Hücre",
    "option2": "Tanecik (Atom)",
    "option3": "Kristal",
    "option4": "Mikrop",
    "correctAnswer": 1,
    "difficulty": "easy",
    "explanation": "Tüm maddeler hareketli taneciklerden (atomlardan) oluşur.",
    "theme": "4. Ünite: Madde ve Isı"
  },
  {
    "grade": 6,
    "subject": "Fen Bilimleri",
    "unit": "4. Ünite: Madde ve Isı",
    "question": "Maddenin hangi halinde tanecikler arası boşluk EN FAZLADIR ve sadece öteleme hareketi yaparlar?",
    "option1": "Katı",
    "option2": "Sıvı",
    "option3": "Gaz",
    "option4": "Hepsi aynıdır",
    "correctAnswer": 2,
    "difficulty": "medium",
    "explanation": "Gazlarda tanecikler birbirinden bağımsız, çok uzaktır ve her yöne uçar (öteleme).",
    "theme": "4. Ünite: Madde ve Isı"
  },
  {
    "grade": 6,
    "subject": "Fen Bilimleri",
    "unit": "4. Ünite: Madde ve Isı",
    "question": "Birim hacimdeki madde miktarına (Kütle ÷ Hacim) ne ad verilir?",
    "option1": "Yoğunluk (Özkütle)",
    "option2": "Ağırlık",
    "option3": "Isı",
    "option4": "Basınç",
    "correctAnswer": 0,
    "difficulty": "easy",
    "explanation": "Maddelerin yoğunluğu (d), kütlesinin hacmine bölünmesiyle hesaplanır (d = m / V).",
    "theme": "4. Ünite: Madde ve Isı"
  },
  {
    "grade": 6,
    "subject": "Fen Bilimleri",
    "unit": "4. Ünite: Madde ve Isı",
    "question": "Kütlesi 100 gram, hacmi 20 cm³ olan bir cismin yoğunluğu kaçtır?",
    "option1": "2000 g/cm³",
    "option2": "80 g/cm³",
    "option3": "5 g/cm³",
    "option4": "120 g/cm³",
    "correctAnswer": 2,
    "difficulty": "medium",
    "explanation": "Yoğunluk = Kütle / Hacim. 100 / 20 = 5 g/cm³.",
    "theme": "4. Ünite: Madde ve Isı"
  },
  {
    "grade": 6,
    "subject": "Fen Bilimleri",
    "unit": "4. Ünite: Madde ve Isı",
    "question": "Aynı hacimde su ve zeytinyağı bir kaba konulduğunda yağın üste çıkmasının sebebi nedir?",
    "option1": "Yağın renginin sarı olması",
    "option2": "Suyun yoğunluğunun, yağın yoğunluğundan BÜYÜK olması",
    "option3": "Yağın daha sıcak olması",
    "option4": "Suyun yağdan hafif olması",
    "correctAnswer": 1,
    "difficulty": "medium",
    "explanation": "Birbirine karışmayan sıvılarda yoğunluğu küçük olan üste çıkar, büyük olan (su) dibe çöker.",
    "theme": "4. Ünite: Madde ve Isı"
  },
  {
    "grade": 6,
    "subject": "Fen Bilimleri",
    "unit": "4. Ünite: Madde ve Isı",
    "question": "Kışın göllerin üstten donmaya başlamasının (buzun suda yüzmesinin) canlılar için önemi nedir?",
    "option1": "Balıkların buzda kaymasını sağlar.",
    "option2": "Su altındaki sıcaklığı koruyarak su canlılarının yaşamasını sağlar.",
    "option3": "Suyun kirlenmesini engeller.",
    "option4": "Bir faydası yoktur.",
    "correctAnswer": 1,
    "difficulty": "hard",
    "explanation": "Buz suya göre daha az yoğundur, yüzer ve alttaki suyun donmasını engelleyerek canlı yaşamını korur.",
    "theme": "4. Ünite: Madde ve Isı"
  },
  {
    "grade": 6,
    "subject": "Fen Bilimleri",
    "unit": "4. Ünite: Madde ve Isı",
    "question": "Isıyı iyi iletmeyen (ısı yalıtkanı) maddelere örnek hangisidir?",
    "option1": "Bakır tel",
    "option2": "Demir tencere",
    "option3": "Plastik köpük (Strafor)",
    "option4": "Altın yüzük",
    "correctAnswer": 2,
    "difficulty": "easy",
    "explanation": "Metaller iyi iletkendir, plastik ve strafor iyi yalıtkandır.",
    "theme": "4. Ünite: Madde ve Isı"
  },
  {
    "grade": 6,
    "subject": "Fen Bilimleri",
    "unit": "4. Ünite: Madde ve Isı",
    "question": "Binalarda mantolama (yalıtım) yapılmasının asıl amacı nedir?",
    "option1": "Binayı güzelleştirmek",
    "option2": "Kışın sıcak, yazın serin tutarak enerji tasarrufu sağlamak",
    "option3": "Binayı ağırlaştırmak",
    "option4": "Depreme dayanıklı yapmak",
    "correctAnswer": 1,
    "difficulty": "medium",
    "explanation": "Isı yalıtımı ısı akışını yavaşlatır, faturaları azaltır ve çevre dostudur.",
    "theme": "4. Ünite: Madde ve Isı"
  },
  {
    "grade": 6,
    "subject": "Fen Bilimleri",
    "unit": "4. Ünite: Madde ve Isı",
    "question": "Doğalgaz, LPG ve petrol gazı hangi tür yakıtlara girer?",
    "option1": "Katı yakıtlar",
    "option2": "Sıvı yakıtlar",
    "option3": "Gaz yakıtlar",
    "option4": "Nükleer yakıtlar",
    "correctAnswer": 2,
    "difficulty": "easy",
    "explanation": "İsimlerinde olduğu gibi oda koşullarında gaz halinde bulunurlar.",
    "theme": "4. Ünite: Madde ve Isı"
  },
  {
    "grade": 6,
    "subject": "Fen Bilimleri",
    "unit": "4. Ünite: Madde ve Isı",
    "question": "Kömür zehirlenmelerine neden olan ve sobalardan sızan sinsi, kokusuz gaz hangisidir?",
    "option1": "Oksijen",
    "option2": "Karbonmonoksit",
    "option3": "Azot",
    "option4": "Helyum",
    "correctAnswer": 1,
    "difficulty": "medium",
    "explanation": "Tam yanmamış yakıttan çıkan karbonmonoksit gazı sessiz katil olarak bilinir.",
    "theme": "4. Ünite: Madde ve Isı"
  },
  {
    "grade": 6,
    "subject": "Fen Bilimleri",
    "unit": "5. Ünite: Ses ve Özellikleri",
    "question": "Ses nasıl bir yayılma gösterir?",
    "option1": "Düz çizgiler halinde",
    "option2": "Dalgalar halinde",
    "option3": "Işınlar halinde",
    "option4": "Zikzak çizerek",
    "correctAnswer": 1,
    "difficulty": "easy",
    "explanation": "Ses, titreşimler sonucu oluşur ve ortamda dalgalar halinde yayılır.",
    "theme": "5. Ünite: Ses ve Özellikleri"
  },
  {
    "grade": 6,
    "subject": "Fen Bilimleri",
    "unit": "5. Ünite: Ses ve Özellikleri",
    "question": "Sesin yayılabilmesi için MUTLAKA neye ihtiyaç vardır?",
    "option1": "Işığa",
    "option2": "Karanlığa",
    "option3": "Maddesel bir ortama (Katı, Sıvı, Gaz)",
    "option4": "Elektriğe",
    "correctAnswer": 2,
    "difficulty": "medium",
    "explanation": "Ses maddesel (tanecikli) bir ortama ihtiyaç duyar, bu yüzden uzayda yayılmaz.",
    "theme": "5. Ünite: Ses ve Özellikleri"
  },
  {
    "grade": 6,
    "subject": "Fen Bilimleri",
    "unit": "5. Ünite: Ses ve Özellikleri",
    "question": "Ses en hızlı hangi ortamda yayılır?",
    "option1": "Gaz",
    "option2": "Sıvı",
    "option3": "Katı",
    "option4": "Boşluk",
    "correctAnswer": 2,
    "difficulty": "easy",
    "explanation": "Katılarda tanecikler birbirine çok yakın olduğu için titreşim en hızlı iletilir.",
    "theme": "5. Ünite: Ses ve Özellikleri"
  },
  {
    "grade": 6,
    "subject": "Fen Bilimleri",
    "unit": "5. Ünite: Ses ve Özellikleri",
    "question": "Uzayda güneşteki dev patlamaların sesini dünyadan neden DUVAYAMAYIZ?",
    "option1": "Kulaklarımız çok uzak olduğu için",
    "option2": "Uzayda hava (madde) olmadığı için ses boşlukta yayılamaz",
    "option3": "Güneş sesi içine çektiği için",
    "option4": "Işık sesten hızlı olduğu için",
    "correctAnswer": 1,
    "difficulty": "medium",
    "explanation": "Ses boşlukta ilerleyemediği için uzaydaki sesler bize ulaşmaz.",
    "theme": "5. Ünite: Ses ve Özellikleri"
  },
  {
    "grade": 6,
    "subject": "Fen Bilimleri",
    "unit": "5. Ünite: Ses ve Özellikleri",
    "question": "Dağa karşı bağıran bir kişinin sesini birkaç saniye sonra tekrar duymasına ne ad verilir?",
    "option1": "Yankı (Yansıma)",
    "option2": "Soğurulma",
    "option3": "Yalıtım",
    "option4": "Titreşim",
    "correctAnswer": 0,
    "difficulty": "easy",
    "explanation": "Ses dalgalarının engele çarpıp geri dönmesi yankıdır.",
    "theme": "5. Ünite: Ses ve Özellikleri"
  },
  {
    "grade": 6,
    "subject": "Fen Bilimleri",
    "unit": "5. Ünite: Ses ve Özellikleri",
    "question": "Aşağıdaki malzemelerden hangisi 'Ses Yalıtımı' yapmak için UYGUN DEĞİLDİR?",
    "option1": "Sünger",
    "option2": "Pamuk",
    "option3": "Demir levha",
    "option4": "Keçe",
    "correctAnswer": 2,
    "difficulty": "medium",
    "explanation": "Sert ve pürüzsüz metaller sesi yansıtır/iletir. Gözenekli, yumuşak malzemeler (sünger) sesi hapseder (soğurur).",
    "theme": "5. Ünite: Ses ve Özellikleri"
  },
  {
    "grade": 6,
    "subject": "Fen Bilimleri",
    "unit": "5. Ünite: Ses ve Özellikleri",
    "question": "Yarasalar ve yunuslar karanlıkta yönlerini ve avlarını nasıl bulurlar?",
    "option1": "Güçlü gözleriyle",
    "option2": "Yaydıkları ses dalgalarının yankısını (yansımasını) dinleyerek",
    "option3": "Koku alarak",
    "option4": "Işık yayarak",
    "correctAnswer": 1,
    "difficulty": "hard",
    "explanation": "Doğal bir sonar sistemi kullanırlar. Tiz sesler çıkarıp geri dönen sese göre nesnelerin yerini anlarlar.",
    "theme": "5. Ünite: Ses ve Özellikleri"
  },
  {
    "grade": 6,
    "subject": "Fen Bilimleri",
    "unit": "5. Ünite: Ses ve Özellikleri",
    "question": "Deniz altındaki batık gemilerin veya balık sürülerinin yerini bulmak için hangi ses teknolojisi kullanılır?",
    "option1": "Ultrason",
    "option2": "Radar (Sonar)",
    "option3": "Teleskop",
    "option4": "Stetoskop",
    "correctAnswer": 1,
    "difficulty": "medium",
    "explanation": "Gemilerde kullanılan Sonar cihazı suyun altına ses gönderip yankı ile harita çıkarır.",
    "theme": "5. Ünite: Ses ve Özellikleri"
  },
  {
    "grade": 6,
    "subject": "Fen Bilimleri",
    "unit": "5. Ünite: Ses ve Özellikleri",
    "question": "Gök gürültüsünde neden önce şimşeğin ışığını görür, sonra sesini duyarız?",
    "option1": "Gözlerimiz kulaklarımızdan daha iyi çalıştığı için",
    "option2": "Işık hızının, ses hızından çok daha büyük olması",
    "option3": "Sesin havada yorulması",
    "option4": "Rüzgarın sesi geciktirmesi",
    "correctAnswer": 1,
    "difficulty": "medium",
    "explanation": "Işık hızı saniyede yaklaşık 300.000 km iken, ses hızı saniyede 340 metredir.",
    "theme": "5. Ünite: Ses ve Özellikleri"
  },
  {
    "grade": 6,
    "subject": "Fen Bilimleri",
    "unit": "5. Ünite: Ses ve Özellikleri",
    "question": "Tiyatro, sinema veya cami gibi binalarda sesin dağılmadan en kaliteli şekilde duyulması için yapılan mimari bilimine ne denir?",
    "option1": "Akustik",
    "option2": "Optik",
    "option3": "Biyoloji",
    "option4": "Mekanik",
    "correctAnswer": 0,
    "difficulty": "hard",
    "explanation": "Mimar Sinan'ın da kullandığı sesin kaliteli yayılma/yansımasını ayarlayan bilim dalı akustiktir.",
    "theme": "5. Ünite: Ses ve Özellikleri"
  },
  {
    "grade": 6,
    "subject": "Fen Bilimleri",
    "unit": "6. Ünite: Vücudumuzdaki Sistemler ve Sağlığı",
    "question": "Vücudumuzdaki tüm sistemleri yöneten, denetleyen 'Merkezi Sinir Sistemi'nin patronu hangi organdır?",
    "option1": "Omurilik",
    "option2": "Kalp",
    "option3": "Beyin",
    "option4": "Beyincik",
    "correctAnswer": 2,
    "difficulty": "easy",
    "explanation": "Düşünme, hafıza, öğrenme ve tüm organların denetimi beyin tarafından yapılır.",
    "theme": "6. Ünite: Vücudumuzdaki Sistemler ve Sağlığı"
  },
  {
    "grade": 6,
    "subject": "Fen Bilimleri",
    "unit": "6. Ünite: Vücudumuzdaki Sistemler ve Sağlığı",
    "question": "Vücudumuzun dengesini sağlayan, ip cambazlarının çok gelişmiş olduğu sinir sistemi organı hangisidir?",
    "option1": "Beyin",
    "option2": "Beyincik",
    "option3": "Omurilik soğanı",
    "option4": "Omurilik",
    "correctAnswer": 1,
    "difficulty": "medium",
    "explanation": "Beyincik; kas uyumunu ve vücudun dengede durmasını sağlar.",
    "theme": "6. Ünite: Vücudumuzdaki Sistemler ve Sağlığı"
  },
  {
    "grade": 6,
    "subject": "Fen Bilimleri",
    "unit": "6. Ünite: Vücudumuzdaki Sistemler ve Sağlığı",
    "question": "Solunum, sindirim ve kalp atışı gibi istemsiz çalışan iç organları yöneten ve 'Hayat Düğümü' denen organ hangisidir?",
    "option1": "Beyincik",
    "option2": "Omurilik soğanı",
    "option3": "Böbrek",
    "option4": "Omurilik",
    "correctAnswer": 1,
    "difficulty": "hard",
    "explanation": "Omurilik soğanı hayati önem taşıyan iç organları istemsiz olarak yönetir.",
    "theme": "6. Ünite: Vücudumuzdaki Sistemler ve Sağlığı"
  },
  {
    "grade": 6,
    "subject": "Fen Bilimleri",
    "unit": "6. Ünite: Vücudumuzdaki Sistemler ve Sağlığı",
    "question": "Sobaya değen elimizi aniden, düşünmeden geri çekmemizi (Refleks) sağlayan organımız hangisidir?",
    "option1": "Omurilik",
    "option2": "Beyin",
    "option3": "Omurilik soğanı",
    "option4": "Göz",
    "correctAnswer": 0,
    "difficulty": "medium",
    "explanation": "Omurilik, doğuştan veya sonradan kazanılan hızlı tepkilerin (reflekslerin) merkezidir.",
    "theme": "6. Ünite: Vücudumuzdaki Sistemler ve Sağlığı"
  },
  {
    "grade": 6,
    "subject": "Fen Bilimleri",
    "unit": "6. Ünite: Vücudumuzdaki Sistemler ve Sağlığı",
    "question": "Kan şekerini ayarlayan 'insülin' ve 'glukagon' hormonlarını salgılayan iç salgı bezi hangisidir?",
    "option1": "Hipofiz bezi",
    "option2": "Tiroit bezi",
    "option3": "Pankreas",
    "option4": "Böbrek üstü bezi",
    "correctAnswer": 2,
    "difficulty": "medium",
    "explanation": "Pankreas şeker metabolizmasını dengeleyen hayati hormonları üretir.",
    "theme": "6. Ünite: Vücudumuzdaki Sistemler ve Sağlığı"
  },
  {
    "grade": 6,
    "subject": "Fen Bilimleri",
    "unit": "6. Ünite: Vücudumuzdaki Sistemler ve Sağlığı",
    "question": "Korku, heyecan ve öfke anında salgılanarak kalp atışımızı hızlandıran hormon hangisidir?",
    "option1": "Büyüme hormonu",
    "option2": "Adrenalin",
    "option3": "Tiroksin",
    "option4": "İnsülin",
    "correctAnswer": 1,
    "difficulty": "easy",
    "explanation": "Böbrek üstü bezinden salgılanan adrenalin heyecan durumlarında artar.",
    "theme": "6. Ünite: Vücudumuzdaki Sistemler ve Sağlığı"
  },
  {
    "grade": 6,
    "subject": "Fen Bilimleri",
    "unit": "6. Ünite: Vücudumuzdaki Sistemler ve Sağlığı",
    "question": "Göze rengini veren ve göze gelen ışık miktarını (göz bebeğini) ayarlayan kısım neresidir?",
    "option1": "Kornea (Saydam tabaka)",
    "option2": "İris",
    "option3": "Sarı leke",
    "option4": "Kör nokta",
    "correctAnswer": 1,
    "difficulty": "hard",
    "explanation": "İris gözün renkli kısmıdır ve ortasındaki deliği büzüp açarak ışığı ayarlar.",
    "theme": "6. Ünite: Vücudumuzdaki Sistemler ve Sağlığı"
  },
  {
    "grade": 6,
    "subject": "Fen Bilimleri",
    "unit": "6. Ünite: Vücudumuzdaki Sistemler ve Sağlığı",
    "question": "Burnumuz kapalıyken yediğimiz yemeğin tadını iyi alamamamızın sebebi nedir?",
    "option1": "Tat tomurcuklarının bozulması",
    "option2": "Koku alma ile tat alma duyularının beyinde ortak ve beraber çalışması",
    "option3": "Dişlerimizin zayıflaması",
    "option4": "Yemeğin soğuması",
    "correctAnswer": 1,
    "difficulty": "medium",
    "explanation": "Tat ve koku alma merkezleri beyinde yardımlaştığı için koku alamadığımızda tat da algılanamaz.",
    "theme": "6. Ünite: Vücudumuzdaki Sistemler ve Sağlığı"
  },
  {
    "grade": 6,
    "subject": "Fen Bilimleri",
    "unit": "6. Ünite: Vücudumuzdaki Sistemler ve Sağlığı",
    "question": "Deri sağlığımızı korumak için aşağıdakilerden hangisi YANLIŞTIR?",
    "option1": "Düzenli banyo yapmak",
    "option2": "Güneşte uzun saatler (öğlen) korumasız kalmak",
    "option3": "Bol su içmek",
    "option4": "Temiz giysiler giymek",
    "correctAnswer": 1,
    "difficulty": "easy",
    "explanation": "Aşırı güneş ışığı (UV) deri kanserine ve yanıklara yol açabilir.",
    "theme": "6. Ünite: Vücudumuzdaki Sistemler ve Sağlığı"
  },
  {
    "grade": 6,
    "subject": "Fen Bilimleri",
    "unit": "6. Ünite: Vücudumuzdaki Sistemler ve Sağlığı",
    "question": "Bebeklikten yetişkinliğe kadar boy uzamasını ve gelişimi sağlayan, Hipofiz bezinden salgılanan hormon nedir?",
    "option1": "Büyüme hormonu",
    "option2": "Tiroksin",
    "option3": "Adrenalin",
    "option4": "Glukagon",
    "correctAnswer": 0,
    "difficulty": "easy",
    "explanation": "Hipofiz bezi beynin tabanında bulunur ve büyümeyi kontrol eder.",
    "theme": "6. Ünite: Vücudumuzdaki Sistemler ve Sağlığı"
  },
  {
    "grade": 6,
    "subject": "Fen Bilimleri",
    "unit": "7. Ünite: Elektriğin İletimi",
    "question": "Elektrik enerjisini üzerinden rahatça geçiren maddelere ne ad verilir?",
    "option1": "Yalıtkan",
    "option2": "İletken",
    "option3": "Saydam",
    "option4": "Dirençli",
    "correctAnswer": 1,
    "difficulty": "easy",
    "explanation": "Metaller gibi elektriğin akmasına izin veren maddeler iletkendir.",
    "theme": "7. Ünite: Elektriğin İletimi"
  },
  {
    "grade": 6,
    "subject": "Fen Bilimleri",
    "unit": "7. Ünite: Elektriğin İletimi",
    "question": "Aşağıdakilerden hangisi elektriği İYİ İLETEN bir sıvıdır?",
    "option1": "Saf su",
    "option2": "Şekerli su",
    "option3": "Tuzlu su",
    "option4": "Sıvı yağ",
    "correctAnswer": 2,
    "difficulty": "medium",
    "explanation": "Tuzlu su veya limonlu su (asit/baz/tuz çözeltileri) çok iyi elektrik iletir. Saf su ve şekerli su yalıtkandır.",
    "theme": "7. Ünite: Elektriğin İletimi"
  },
  {
    "grade": 6,
    "subject": "Fen Bilimleri",
    "unit": "7. Ünite: Elektriğin İletimi",
    "question": "Prizleri ve kabloları tutarken elektrik çarpmaması için dış kısımları hangi maddeden yapılır?",
    "option1": "Bakır",
    "option2": "Altın",
    "option3": "Plastik (Yalıtkan)",
    "option4": "Demir",
    "correctAnswer": 2,
    "difficulty": "easy",
    "explanation": "Plastik elektriği geçirmediği için (yalıtkan) güvenlik amacıyla kaplama olarak kullanılır.",
    "theme": "7. Ünite: Elektriğin İletimi"
  },
  {
    "grade": 6,
    "subject": "Fen Bilimleri",
    "unit": "7. Ünite: Elektriğin İletimi",
    "question": "Maddelerin elektrik enerjisinin geçişine karşı gösterdiği zorluğa ne ad verilir?",
    "option1": "İletkenlik",
    "option2": "Elektriksel direnç",
    "option3": "Voltaj",
    "option4": "Anahtar",
    "correctAnswer": 1,
    "difficulty": "medium",
    "explanation": "Her madde elektriğe bir miktar karşı koyar, buna direnç denir.",
    "theme": "7. Ünite: Elektriğin İletimi"
  },
  {
    "grade": 6,
    "subject": "Fen Bilimleri",
    "unit": "7. Ünite: Elektriğin İletimi",
    "question": "Elektrik devresindeki direnci DEĞİŞTİREREK ampulün parlaklığını artırıp azaltan sürgülü alete ne denir?",
    "option1": "Reosta (Değişken Direnç)",
    "option2": "Ampermetre",
    "option3": "Pil yatağı",
    "option4": "Sigorta",
    "correctAnswer": 0,
    "difficulty": "hard",
    "explanation": "Reosta, direncin boyunu uzatıp kısaltarak devreden geçen akımı, dolayısıyla parlaklığı ayarlar.",
    "theme": "7. Ünite: Elektriğin İletimi"
  },
  {
    "grade": 6,
    "subject": "Fen Bilimleri",
    "unit": "7. Ünite: Elektriğin İletimi",
    "question": "Kablodaki iletken telin UZUNLUĞU arttıkça elektrik direnci nasıl değişir?",
    "option1": "Direnç azalır",
    "option2": "Direnç değişmez",
    "option3": "Direnç artar",
    "option4": "Elektrik hiç geçmez",
    "correctAnswer": 2,
    "difficulty": "medium",
    "explanation": "Uzun yolda yürümek zorlaştığı gibi, iletkenin boyu uzadıkça elektriğe karşı direnç artar.",
    "theme": "7. Ünite: Elektriğin İletimi"
  },
  {
    "grade": 6,
    "subject": "Fen Bilimleri",
    "unit": "7. Ünite: Elektriğin İletimi",
    "question": "İletken telin DİKKESİT ALANI (kalınlığı) artarsa direnci nasıl etkilenir?",
    "option1": "Direnç azalır (Akım rahat geçer)",
    "option2": "Direnç artar",
    "option3": "Direnç sıfır olur",
    "option4": "Değişmez",
    "correctAnswer": 0,
    "difficulty": "hard",
    "explanation": "Kalın borudan suyun rahat geçmesi gibi, kalın telden de elektrik rahat geçer (Direnç düşüktür).",
    "theme": "7. Ünite: Elektriğin İletimi"
  },
  {
    "grade": 6,
    "subject": "Fen Bilimleri",
    "unit": "7. Ünite: Elektriğin İletimi",
    "question": "Ampulün içinde parlayarak ışık saçan, direnci çok yüksek (Tungsten metalinden) ince kıvrımlı tele ne denir?",
    "option1": "Duy",
    "option2": "Priz",
    "option3": "Filaman",
    "option4": "Anahtar",
    "correctAnswer": 2,
    "difficulty": "hard",
    "explanation": "Filamanın direnci çok yüksektir, zorlanan elektrik onu akkor hale getirir ve ışık saçar.",
    "theme": "7. Ünite: Elektriğin İletimi"
  },
  {
    "grade": 6,
    "subject": "Fen Bilimleri",
    "unit": "7. Ünite: Elektriğin İletimi",
    "question": "Aşağıdakilerden hangisi bir YALITKAN örneğidir?",
    "option1": "Gümüş kolye",
    "option2": "Çivi",
    "option3": "Kurşun kalem içi (grafit)",
    "option4": "Kuru tahta",
    "correctAnswer": 3,
    "difficulty": "easy",
    "explanation": "Kuru ahşap/tahta elektriği iletmez (yalıtkandır). Ancak ıslanırsa iletken olabilir.",
    "theme": "7. Ünite: Elektriğin İletimi"
  },
  {
    "grade": 6,
    "subject": "Fen Bilimleri",
    "unit": "7. Ünite: Elektriğin İletimi",
    "question": "Ampul parlaklığını EN FAZLA yapmak için kullanılacak tel nasıl olmalıdır?",
    "option1": "Uzun ve ince",
    "option2": "Uzun ve kalın",
    "option3": "Kısa ve kalın",
    "option4": "Kısa ve ince",
    "correctAnswer": 2,
    "difficulty": "medium",
    "explanation": "Parlaklık için direncin en az olması gerekir. En az direnç 'Kısa ve Kalın' tellerdedir.",
    "theme": "7. Ünite: Elektriğin İletimi"
  }
]